{"type":"attendee.created","data":{"id":34668,"first_name":"Marcin","last_name":"Koziej","email":"dump2@cahoots.pl","phone_number":"+48504921992","postcode":"02-707","country":"","attending_status":"attending","join_organisation":true,"join_group":null,"user_ip":"89.65.80.87","additional_fields":{},"member":{"id":16118128,"created_at":"2016-08-31T18:03:22.856+02:00"},"event":{"url":"https://naszademokracja.pl/events/wroclaw-jedzie-demonstrowac-przeciw-ttip-i-ceta","slug":"wroclaw-jedzie-demonstrowac-przeciw-ttip-i-ceta"},"created_at":"2016-10-10T13:38:57.023+02:00"},"jid":"12d097e1681fb769bd8c0d62"}
